Metadata-Version: 1.0
Name: Gausdis
Version: 1.0
Summary: Gaussian and Binomial distributions
Home-page: UNKNOWN
Author: Wenjie Wang
Author-email: wang2021@brandeis.edu
License: UNKNOWN
Platform: UNKNOWN
